{"cameraMode":{"drawMode":0,"name":"Shaded","section":"Shading Mode"},"sceneLighting":true,"audioPlay":false,"sceneViewState":{"m_AlwaysRefresh":false,"showFog":true,"showSkybox":true,"showFlares":true,"showImageEffects":true,"showParticleSystems":true,"showVisualEffectGraphs":true,"m_FxEnabled":true},"in2DMode":false,"pivot":{"x":-0.7899247407913208,"y":-1.0396816730499268,"z":1.911329984664917},"rotation":{"x":-0.10089778155088425,"y":0.8990916609764099,"z":-0.303757905960083,"w":-0.29864731431007388},"size":1.6578459739685059,"orthographic":false}